{
  "folders": [
    {
      "id": "f1",
      "name": "Getting Started"
    },
    {
      "id": "f2",
      "name": "Personal"
    },
    {
      "name": "Test",
      "id": "23db389b-c647-47eb-a361-42b8689b1eb8"
    },
    {
      "name": "test",
      "id": "d150150d-a663-4173-a088-ac1f955c18cc"
    },
    {
      "name": "test",
      "id": "a789940f-1a95-4408-9624-82dbc76bd5c6"
    },
    {
      "name": "Test1000",
      "id": "079c3050-8d45-4635-85bd-9ae578809b19"
    }
  ],
  "notes": [
    {
      "id": "n1",
      "folderId": "f1",
      "title": "Welcome to NotePad",
      "content": "# Welcome to NotePad!\n\nThis is your new favorite note-taking application. Here's what you can do:\n\n## Features\n- Create and organize notes in folders\n- Format your notes with Markdown\n- Easily navigate between notes\n- Create new folders to organize your work\n- Dark mode support\n\n## Getting Started\n1. Click on \"New Note\" to create a new note\n2. Use the \"New Folder\" button to create a new folder\n3. Click on any note to view and edit its content\n4. Save automatically as you type\n\nFeel free to explore and organize your thoughts!"
    },
    {
      "id": "n2",
      "folderId": "f2",
      "title": "Shopping List",
      "content": "# Shopping List\n\n- Milk\n- Eggs\n- Bread\n- Coffee\n- Apples\n- Pasta\n- Tomato sauce"
    },
    {
      "id": "n3",
      "folderId": "f2",
      "title": "Project Ideas",
      "content": "# Future Project Ideas\n\n1. Learn a new programming language\n2. Build a mobile app\n3. Create a personal website\n4. Contribute to open source"
    },
    {
      "folderId": "f1",
      "content": "Lalalla",
      "id": "7d92e884-4264-4834-b10f-2058567d39e0"
    },
    {
      "folderId": "f1",
      "content": "Heyyyyy",
      "id": "23b9acac-92a7-4f3a-8286-80b3043bae4c"
    },
    {
      "folderId": "f1",
      "content": "",
      "id": "4045cd06-213b-4b47-8b31-a8340a78e4ae"
    },
    {
      "folderId": "f1",
      "content": "",
      "id": "2a718d00-01d1-4c45-961d-17cfff127736"
    },
    {
      "folderId": "079c3050-8d45-4635-85bd-9ae578809b19",
      "content": "",
      "id": "0d152879-f6a6-41d3-a63a-2305cf71e95d"
    },
    {
      "folderId": "079c3050-8d45-4635-85bd-9ae578809b19",
      "content": "",
      "id": "4c4a0897-c02a-4814-a019-845716749b42"
    },
    {
      "folderId": "079c3050-8d45-4635-85bd-9ae578809b19",
      "title": "testtt naam?",
      "content": "sla op fdkljfkdlkfd",
      "id": "881076a1-2188-4cfe-be6c-61dbed69d4d3"
    },
    {
      "folderId": "f1",
      "title": "Testt",
      "content": "",
      "id": "841761c3-2c43-4954-bf87-a9f2f2ee9fd3"
    },
    {
      "folderId": "f2",
      "title": "Devine TO DO",
      "content": "Hello Klik klik CSS Wat doe je!?Waaaaaaaaaaaaaaaaaaaaarom is dit zo klein\n\n\nen moet ik scrollen!?",
      "id": "e289a936-07ca-4f80-a45d-6cd4b1cd0e72"
    }
  ]
}